{"pgs":[{"ibl":[{"tlx":59,"tly":29,"brx":3190,"bry":4965}],"tbl":[],"clb":[],"gbl":[],"lns":null,"ifl":"image-001","tlx":0,"tly":0,"brx":3240,"bry":5000},{"ibl":[{"tlx":37,"tly":25,"brx":1037,"bry":1585}],"tbl":[],"clb":[],"gbl":[],"lns":null,"ifl":"image-002","tlx":0,"tly":0,"brx":1074,"bry":1611},{"ibl":[{"tlx":37,"tly":25,"brx":1037,"bry":1585}],"tbl":[],"clb":[],"gbl":[],"lns":null,"ifl":"image-003","tlx":0,"tly":0,"brx":1073,"bry":1610},{"ibl":[{"tlx":37,"tly":25,"brx":1037,"bry":1585}],"tbl":[],"clb":[],"gbl":[],"lns":null,"ifl":"image-004","tlx":0,"tly":0,"brx":1066,"bry":1605},{"ibl":[],"tbl":[],"clb":[],"gbl":[],"lns":null,"ifl":"image-005","tlx":0,"tly":0,"brx":1068,"bry":1607},{"ibl":[],"tbl":[],"clb":[],"gbl":[],"lns":null,"ifl":"image-006","tlx":0,"tly":0,"brx":1066,"bry":1606},{"ibl":[],"tbl":[],"clb":[],"gbl":[],"lns":null,"ifl":"image-007","tlx":0,"tly":0,"brx":1067,"bry":1606},{"ibl":[],"tbl":[],"clb":[],"gbl":[],"lns":null,"ifl":"image-008","tlx":0,"tly":0,"brx":1067,"bry":1606},{"ibl":[],"tbl":[],"clb":[],"gbl":[],"lns":null,"ifl":"image-009","tlx":0,"tly":0,"brx":1067,"bry":1606},{"ibl":[],"tbl":[],"clb":[],"gbl":[],"lns":null,"ifl":"image-010","tlx":0,"tly":0,"brx":1066,"bry":1606},{"ibl":[],"tbl":[],"clb":[],"gbl":[],"lns":null,"ifl":"image-011","tlx":0,"tly":0,"brx":1066,"bry":1606},{"ibl":[],"tbl":[],"clb":[],"gbl":[],"lns":null,"ifl":"image-012","tlx":0,"tly":0,"brx":1066,"bry":1605},{"ibl":[],"tbl":[],"clb":[],"gbl":[],"lns":null,"ifl":"image-013","tlx":0,"tly":0,"brx":1066,"bry":1605},{"ibl":[],"tbl":[],"clb":[],"gbl":[],"lns":null,"ifl":"image-014","tlx":0,"tly":0,"brx":1066,"bry":1606},{"ibl":[],"tbl":[],"clb":[],"gbl":[],"lns":null,"ifl":"image-015","tlx":0,"tly":0,"brx":1067,"bry":1606},{"ibl":[],"tbl":[],"clb":[],"gbl":[],"lns":null,"ifl":"image-016","tlx":0,"tly":0,"brx":1066,"bry":1606},{"ibl":[],"tbl":[],"clb":[],"gbl":[],"lns":null,"ifl":"image-017","tlx":0,"tly":0,"brx":1067,"bry":1606},{"ibl":[],"tbl":[],"clb":[],"gbl":[],"lns":null,"ifl":"image-018","tlx":0,"tly":0,"brx":1066,"bry":1605},{"ibl":[],"tbl":[],"clb":[],"gbl":[],"lns":null,"ifl":"image-019","tlx":0,"tly":0,"brx":1074,"bry":1611},{"ibl":[],"tbl":[],"clb":[],"gbl":[],"lns":null,"ifl":"image-020","tlx":0,"tly":0,"brx":1066,"bry":1605},{"ibl":[],"tbl":[],"clb":[],"gbl":[],"lns":null,"ifl":"image-021","tlx":0,"tly":0,"brx":1066,"bry":1606},{"ibl":[],"tbl":[],"clb":[],"gbl":[],"lns":null,"ifl":"image-022","tlx":0,"tly":0,"brx":1066,"bry":1605},{"ibl":[],"tbl":[],"clb":[],"gbl":[],"lns":null,"ifl":"image-023","tlx":0,"tly":0,"brx":1067,"bry":1606},{"ibl":[],"tbl":[],"clb":[],"gbl":[],"lns":null,"ifl":"image-024","tlx":0,"tly":0,"brx":1066,"bry":1605},{"ibl":[],"tbl":[],"clb":[],"gbl":[],"lns":null,"ifl":"image-025","tlx":0,"tly":0,"brx":1066,"bry":1605},{"ibl":[],"tbl":[],"clb":[],"gbl":[],"lns":null,"ifl":"image-026","tlx":0,"tly":0,"brx":1066,"bry":1606},{"ibl":[],"tbl":[],"clb":[],"gbl":[],"lns":null,"ifl":"image-027","tlx":0,"tly":0,"brx":1066,"bry":1606},{"ibl":[],"tbl":[],"clb":[],"gbl":[],"lns":null,"ifl":"image-028","tlx":0,"tly":0,"brx":1066,"bry":1605},{"ibl":[],"tbl":[],"clb":[],"gbl":[],"lns":null,"ifl":"image-029","tlx":0,"tly":0,"brx":1070,"bry":1608},{"ibl":[],"tbl":[],"clb":[],"gbl":[],"lns":null,"ifl":"image-030","tlx":0,"tly":0,"brx":1066,"bry":1605},{"ibl":[],"tbl":[],"clb":[],"gbl":[],"lns":null,"ifl":"image-031","tlx":0,"tly":0,"brx":1073,"bry":1610},{"ibl":[],"tbl":[],"clb":[],"gbl":[],"lns":null,"ifl":"image-032","tlx":0,"tly":0,"brx":1066,"bry":1606},{"ibl":[],"tbl":[],"clb":[],"gbl":[],"lns":null,"ifl":"image-033","tlx":0,"tly":0,"brx":1067,"bry":1606},{"ibl":[],"tbl":[],"clb":[],"gbl":[],"lns":null,"ifl":"image-034","tlx":0,"tly":0,"brx":1066,"bry":1606},{"ibl":[],"tbl":[],"clb":[],"gbl":[],"lns":null,"ifl":"image-035","tlx":0,"tly":0,"brx":1069,"bry":1607},{"ibl":[],"tbl":[],"clb":[],"gbl":[],"lns":null,"ifl":"image-036","tlx":0,"tly":0,"brx":1066,"bry":1605},{"ibl":[],"tbl":[],"clb":[],"gbl":[],"lns":null,"ifl":"image-037","tlx":0,"tly":0,"brx":1067,"bry":1606},{"ibl":[],"tbl":[],"clb":[],"gbl":[],"lns":null,"ifl":"image-038","tlx":0,"tly":0,"brx":1066,"bry":1606},{"ibl":[],"tbl":[],"clb":[],"gbl":[],"lns":null,"ifl":"image-039","tlx":0,"tly":0,"brx":1068,"bry":1607},{"ibl":[],"tbl":[],"clb":[],"gbl":[],"lns":null,"ifl":"image-040","tlx":0,"tly":0,"brx":1066,"bry":1605},{"ibl":[],"tbl":[],"clb":[],"gbl":[],"lns":null,"ifl":"image-041","tlx":0,"tly":0,"brx":1066,"bry":1605},{"ibl":[],"tbl":[],"clb":[],"gbl":[],"lns":null,"ifl":"image-042","tlx":0,"tly":0,"brx":1067,"bry":1606},{"ibl":[],"tbl":[],"clb":[],"gbl":[],"lns":null,"ifl":"image-043","tlx":0,"tly":0,"brx":1067,"bry":1606},{"ibl":[],"tbl":[],"clb":[],"gbl":[],"lns":null,"ifl":"image-044","tlx":0,"tly":0,"brx":1066,"bry":1606},{"ibl":[],"tbl":[],"clb":[],"gbl":[],"lns":null,"ifl":"image-045","tlx":0,"tly":0,"brx":1069,"bry":1607},{"ibl":[],"tbl":[],"clb":[],"gbl":[],"lns":null,"ifl":"image-046","tlx":0,"tly":0,"brx":1066,"bry":1605},{"ibl":[],"tbl":[],"clb":[],"gbl":[],"lns":null,"ifl":"image-047","tlx":0,"tly":0,"brx":1072,"bry":1610},{"ibl":[],"tbl":[],"clb":[],"gbl":[],"lns":null,"ifl":"image-048","tlx":0,"tly":0,"brx":1066,"bry":1605},{"ibl":[],"tbl":[],"clb":[],"gbl":[],"lns":null,"ifl":"image-049","tlx":0,"tly":0,"brx":1066,"bry":1606},{"ibl":[],"tbl":[],"clb":[],"gbl":[],"lns":null,"ifl":"image-050","tlx":0,"tly":0,"brx":1070,"bry":1608},{"ibl":[],"tbl":[],"clb":[],"gbl":[],"lns":null,"ifl":"image-051","tlx":0,"tly":0,"brx":1069,"bry":1607},{"ibl":[],"tbl":[],"clb":[],"gbl":[],"lns":null,"ifl":"image-052","tlx":0,"tly":0,"brx":1066,"bry":1606},{"ibl":[],"tbl":[],"clb":[],"gbl":[],"lns":null,"ifl":"image-053","tlx":0,"tly":0,"brx":1066,"bry":1605},{"ibl":[],"tbl":[],"clb":[],"gbl":[],"lns":null,"ifl":"image-054","tlx":0,"tly":0,"brx":1066,"bry":1606},{"ibl":[],"tbl":[],"clb":[],"gbl":[],"lns":null,"ifl":"image-055","tlx":0,"tly":0,"brx":1066,"bry":1605},{"ibl":[],"tbl":[],"clb":[],"gbl":[],"lns":null,"ifl":"image-056","tlx":0,"tly":0,"brx":1066,"bry":1605},{"ibl":[],"tbl":[],"clb":[],"gbl":[],"lns":null,"ifl":"image-057","tlx":0,"tly":0,"brx":1066,"bry":1606},{"ibl":[],"tbl":[],"clb":[],"gbl":[],"lns":null,"ifl":"image-058","tlx":0,"tly":0,"brx":1066,"bry":1606},{"ibl":[],"tbl":[],"clb":[],"gbl":[],"lns":null,"ifl":"image-059","tlx":0,"tly":0,"brx":1066,"bry":1605},{"ibl":[],"tbl":[],"clb":[],"gbl":[],"lns":null,"ifl":"image-060","tlx":0,"tly":0,"brx":1067,"bry":1606},{"ibl":[],"tbl":[],"clb":[],"gbl":[],"lns":null,"ifl":"image-061","tlx":0,"tly":0,"brx":1066,"bry":1606},{"ibl":[],"tbl":[],"clb":[],"gbl":[],"lns":null,"ifl":"image-062","tlx":0,"tly":0,"brx":1067,"bry":1606},{"ibl":[],"tbl":[],"clb":[],"gbl":[],"lns":null,"ifl":"image-063","tlx":0,"tly":0,"brx":1066,"bry":1606},{"ibl":[],"tbl":[],"clb":[],"gbl":[],"lns":null,"ifl":"image-064","tlx":0,"tly":0,"brx":1066,"bry":1606},{"ibl":[],"tbl":[],"clb":[],"gbl":[],"lns":null,"ifl":"image-065","tlx":0,"tly":0,"brx":1066,"bry":1605},{"ibl":[],"tbl":[],"clb":[],"gbl":[],"lns":null,"ifl":"image-066","tlx":0,"tly":0,"brx":1066,"bry":1605},{"ibl":[],"tbl":[],"clb":[],"gbl":[],"lns":null,"ifl":"image-067","tlx":0,"tly":0,"brx":1066,"bry":1605},{"ibl":[],"tbl":[],"clb":[],"gbl":[],"lns":null,"ifl":"image-068","tlx":0,"tly":0,"brx":1066,"bry":1606},{"ibl":[],"tbl":[],"clb":[],"gbl":[],"lns":null,"ifl":"image-069","tlx":0,"tly":0,"brx":1066,"bry":1606},{"ibl":[],"tbl":[],"clb":[],"gbl":[],"lns":null,"ifl":"image-070","tlx":0,"tly":0,"brx":1066,"bry":1606},{"ibl":[],"tbl":[],"clb":[],"gbl":[],"lns":null,"ifl":"image-071","tlx":0,"tly":0,"brx":1066,"bry":1606},{"ibl":[],"tbl":[],"clb":[],"gbl":[],"lns":null,"ifl":"image-072","tlx":0,"tly":0,"brx":1066,"bry":1606},{"ibl":[],"tbl":[],"clb":[],"gbl":[],"lns":null,"ifl":"image-073","tlx":0,"tly":0,"brx":1066,"bry":1606},{"ibl":[],"tbl":[],"clb":[],"gbl":[],"lns":null,"ifl":"image-074","tlx":0,"tly":0,"brx":1066,"bry":1605},{"ibl":[],"tbl":[],"clb":[],"gbl":[],"lns":null,"ifl":"image-075","tlx":0,"tly":0,"brx":1066,"bry":1606},{"ibl":[],"tbl":[],"clb":[],"gbl":[],"lns":null,"ifl":"image-076","tlx":0,"tly":0,"brx":1066,"bry":1606},{"ibl":[],"tbl":[],"clb":[],"gbl":[],"lns":null,"ifl":"image-077","tlx":0,"tly":0,"brx":1066,"bry":1606},{"ibl":[],"tbl":[],"clb":[],"gbl":[],"lns":null,"ifl":"image-078","tlx":0,"tly":0,"brx":1066,"bry":1606},{"ibl":[],"tbl":[],"clb":[],"gbl":[],"lns":null,"ifl":"image-079","tlx":0,"tly":0,"brx":1066,"bry":1605},{"ibl":[],"tbl":[],"clb":[],"gbl":[],"lns":null,"ifl":"image-080","tlx":0,"tly":0,"brx":1069,"bry":1608},{"ibl":[],"tbl":[],"clb":[],"gbl":[],"lns":null,"ifl":"image-081","tlx":0,"tly":0,"brx":1067,"bry":1606},{"ibl":[],"tbl":[],"clb":[],"gbl":[],"lns":null,"ifl":"image-082","tlx":0,"tly":0,"brx":1066,"bry":1605},{"ibl":[],"tbl":[],"clb":[],"gbl":[],"lns":null,"ifl":"image-083","tlx":0,"tly":0,"brx":1066,"bry":1605},{"ibl":[],"tbl":[],"clb":[],"gbl":[],"lns":null,"ifl":"image-084","tlx":0,"tly":0,"brx":1066,"bry":1606},{"ibl":[],"tbl":[],"clb":[],"gbl":[],"lns":null,"ifl":"image-085","tlx":0,"tly":0,"brx":1068,"bry":1607},{"ibl":[],"tbl":[],"clb":[],"gbl":[],"lns":null,"ifl":"image-086","tlx":0,"tly":0,"brx":1068,"bry":1607},{"ibl":[],"tbl":[],"clb":[],"gbl":[],"lns":null,"ifl":"image-087","tlx":0,"tly":0,"brx":1066,"bry":1606},{"ibl":[],"tbl":[],"clb":[],"gbl":[],"lns":null,"ifl":"image-088","tlx":0,"tly":0,"brx":1069,"bry":1607},{"ibl":[],"tbl":[],"clb":[],"gbl":[],"lns":null,"ifl":"image-089","tlx":0,"tly":0,"brx":1070,"bry":1608},{"ibl":[],"tbl":[],"clb":[],"gbl":[],"lns":null,"ifl":"image-090","tlx":0,"tly":0,"brx":1066,"bry":1605},{"ibl":[],"tbl":[],"clb":[],"gbl":[],"lns":null,"ifl":"image-091","tlx":0,"tly":0,"brx":1066,"bry":1605},{"ibl":[],"tbl":[],"clb":[],"gbl":[],"lns":null,"ifl":"image-092","tlx":0,"tly":0,"brx":1068,"bry":1607},{"ibl":[],"tbl":[],"clb":[],"gbl":[],"lns":null,"ifl":"image-093","tlx":0,"tly":0,"brx":1066,"bry":1606},{"ibl":[],"tbl":[],"clb":[],"gbl":[],"lns":null,"ifl":"image-094","tlx":0,"tly":0,"brx":1066,"bry":1606},{"ibl":[],"tbl":[],"clb":[],"gbl":[],"lns":null,"ifl":"image-095","tlx":0,"tly":0,"brx":1066,"bry":1606},{"ibl":[],"tbl":[],"clb":[],"gbl":[],"lns":null,"ifl":"image-096","tlx":0,"tly":0,"brx":1066,"bry":1606},{"ibl":[],"tbl":[],"clb":[],"gbl":[],"lns":null,"ifl":"image-097","tlx":0,"tly":0,"brx":1066,"bry":1605},{"ibl":[],"tbl":[],"clb":[],"gbl":[],"lns":null,"ifl":"image-098","tlx":0,"tly":0,"brx":1066,"bry":1606},{"ibl":[],"tbl":[],"clb":[],"gbl":[],"lns":null,"ifl":"image-099","tlx":0,"tly":0,"brx":1066,"bry":1606},{"ibl":[],"tbl":[],"clb":[],"gbl":[],"lns":null,"ifl":"image-100","tlx":0,"tly":0,"brx":1068,"bry":1607},{"ibl":[],"tbl":[],"clb":[],"gbl":[],"lns":null,"ifl":"image-101","tlx":0,"tly":0,"brx":1067,"bry":1606},{"ibl":[],"tbl":[],"clb":[],"gbl":[],"lns":null,"ifl":"image-102","tlx":0,"tly":0,"brx":1067,"bry":1606},{"ibl":[],"tbl":[],"clb":[],"gbl":[],"lns":null,"ifl":"image-103","tlx":0,"tly":0,"brx":1066,"bry":1606},{"ibl":[],"tbl":[],"clb":[],"gbl":[],"lns":null,"ifl":"image-104","tlx":0,"tly":0,"brx":1066,"bry":1606},{"ibl":[],"tbl":[],"clb":[],"gbl":[],"lns":null,"ifl":"image-105","tlx":0,"tly":0,"brx":1066,"bry":1605},{"ibl":[],"tbl":[],"clb":[],"gbl":[],"lns":null,"ifl":"image-106","tlx":0,"tly":0,"brx":1066,"bry":1606},{"ibl":[],"tbl":[],"clb":[],"gbl":[],"lns":null,"ifl":"image-107","tlx":0,"tly":0,"brx":1066,"bry":1605},{"ibl":[],"tbl":[],"clb":[],"gbl":[],"lns":null,"ifl":"image-108","tlx":0,"tly":0,"brx":1069,"bry":1607},{"ibl":[],"tbl":[],"clb":[],"gbl":[],"lns":null,"ifl":"image-109","tlx":0,"tly":0,"brx":1066,"bry":1606},{"ibl":[],"tbl":[],"clb":[],"gbl":[],"lns":null,"ifl":"image-110","tlx":0,"tly":0,"brx":1066,"bry":1606},{"ibl":[],"tbl":[],"clb":[],"gbl":[],"lns":null,"ifl":"image-111","tlx":0,"tly":0,"brx":1067,"bry":1606},{"ibl":[],"tbl":[],"clb":[],"gbl":[],"lns":null,"ifl":"image-112","tlx":0,"tly":0,"brx":1068,"bry":1607},{"ibl":[],"tbl":[],"clb":[],"gbl":[],"lns":null,"ifl":"image-113","tlx":0,"tly":0,"brx":1069,"bry":1607},{"ibl":[],"tbl":[],"clb":[],"gbl":[],"lns":null,"ifl":"image-114","tlx":0,"tly":0,"brx":1066,"bry":1606},{"ibl":[],"tbl":[],"clb":[],"gbl":[],"lns":null,"ifl":"image-115","tlx":0,"tly":0,"brx":1066,"bry":1605},{"ibl":[],"tbl":[],"clb":[],"gbl":[],"lns":null,"ifl":"image-116","tlx":0,"tly":0,"brx":1066,"bry":1606},{"ibl":[],"tbl":[],"clb":[],"gbl":[],"lns":null,"ifl":"image-117","tlx":0,"tly":0,"brx":1066,"bry":1605},{"ibl":[],"tbl":[],"clb":[],"gbl":[],"lns":null,"ifl":"image-118","tlx":0,"tly":0,"brx":1066,"bry":1605},{"ibl":[],"tbl":[],"clb":[],"gbl":[],"lns":null,"ifl":"image-119","tlx":0,"tly":0,"brx":1068,"bry":1607},{"ibl":[],"tbl":[],"clb":[],"gbl":[],"lns":null,"ifl":"image-120","tlx":0,"tly":0,"brx":1066,"bry":1606},{"ibl":[],"tbl":[],"clb":[],"gbl":[],"lns":null,"ifl":"image-121","tlx":0,"tly":0,"brx":1066,"bry":1606},{"ibl":[],"tbl":[],"clb":[],"gbl":[],"lns":null,"ifl":"image-122","tlx":0,"tly":0,"brx":1066,"bry":1605},{"ibl":[],"tbl":[],"clb":[],"gbl":[],"lns":null,"ifl":"image-123","tlx":0,"tly":0,"brx":1066,"bry":1605},{"ibl":[],"tbl":[],"clb":[],"gbl":[],"lns":null,"ifl":"image-124","tlx":0,"tly":0,"brx":1066,"bry":1606},{"ibl":[],"tbl":[],"clb":[],"gbl":[],"lns":null,"ifl":"image-125","tlx":0,"tly":0,"brx":1066,"bry":1606},{"ibl":[],"tbl":[],"clb":[],"gbl":[],"lns":null,"ifl":"image-126","tlx":0,"tly":0,"brx":1066,"bry":1605},{"ibl":[],"tbl":[],"clb":[],"gbl":[],"lns":null,"ifl":"image-127","tlx":0,"tly":0,"brx":1067,"bry":1606},{"ibl":[],"tbl":[],"clb":[],"gbl":[],"lns":null,"ifl":"image-128","tlx":0,"tly":0,"brx":1067,"bry":1606},{"ibl":[],"tbl":[],"clb":[],"gbl":[],"lns":null,"ifl":"image-129","tlx":0,"tly":0,"brx":1067,"bry":1606},{"ibl":[{"tlx":78,"tly":137,"brx":649,"bry":583}],"tbl":[],"clb":[],"gbl":[],"lns":null,"ifl":"image-130","tlx":0,"tly":0,"brx":1066,"bry":1606},{"ibl":[],"tbl":[],"clb":[],"gbl":[],"lns":null,"ifl":"image-131","tlx":0,"tly":0,"brx":1066,"bry":1606},{"ibl":[],"tbl":[],"clb":[],"gbl":[],"lns":null,"ifl":"image-132","tlx":0,"tly":0,"brx":1066,"bry":1605},{"ibl":[],"tbl":[],"clb":[],"gbl":[],"lns":null,"ifl":"image-133","tlx":0,"tly":0,"brx":1067,"bry":1606},{"ibl":[],"tbl":[],"clb":[],"gbl":[],"lns":null,"ifl":"image-134","tlx":0,"tly":0,"brx":1066,"bry":1606},{"ibl":[],"tbl":[],"clb":[],"gbl":[],"lns":null,"ifl":"image-135","tlx":0,"tly":0,"brx":1067,"bry":1606},{"ibl":[],"tbl":[],"clb":[],"gbl":[],"lns":null,"ifl":"image-136","tlx":0,"tly":0,"brx":1066,"bry":1606},{"ibl":[],"tbl":[],"clb":[],"gbl":[],"lns":null,"ifl":"image-137","tlx":0,"tly":0,"brx":1066,"bry":1605},{"ibl":[],"tbl":[],"clb":[],"gbl":[],"lns":null,"ifl":"image-138","tlx":0,"tly":0,"brx":1066,"bry":1605},{"ibl":[],"tbl":[],"clb":[],"gbl":[],"lns":null,"ifl":"image-139","tlx":0,"tly":0,"brx":1066,"bry":1606},{"ibl":[],"tbl":[],"clb":[],"gbl":[],"lns":null,"ifl":"image-140","tlx":0,"tly":0,"brx":1066,"bry":1606},{"ibl":[],"tbl":[],"clb":[],"gbl":[],"lns":null,"ifl":"image-141","tlx":0,"tly":0,"brx":1066,"bry":1606},{"ibl":[],"tbl":[],"clb":[],"gbl":[],"lns":null,"ifl":"image-142","tlx":0,"tly":0,"brx":1066,"bry":1605},{"ibl":[],"tbl":[],"clb":[],"gbl":[],"lns":null,"ifl":"image-143","tlx":0,"tly":0,"brx":1066,"bry":1605},{"ibl":[],"tbl":[],"clb":[],"gbl":[],"lns":null,"ifl":"image-144","tlx":0,"tly":0,"brx":1066,"bry":1605},{"ibl":[],"tbl":[],"clb":[],"gbl":[],"lns":null,"ifl":"image-145","tlx":0,"tly":0,"brx":1066,"bry":1605},{"ibl":[],"tbl":[],"clb":[],"gbl":[],"lns":null,"ifl":"image-146","tlx":0,"tly":0,"brx":1066,"bry":1606},{"ibl":[],"tbl":[],"clb":[],"gbl":[],"lns":null,"ifl":"image-147","tlx":0,"tly":0,"brx":1067,"bry":1606},{"ibl":[],"tbl":[],"clb":[],"gbl":[],"lns":null,"ifl":"image-148","tlx":0,"tly":0,"brx":1066,"bry":1606},{"ibl":[],"tbl":[],"clb":[],"gbl":[],"lns":null,"ifl":"image-149","tlx":0,"tly":0,"brx":1066,"bry":1606},{"ibl":[],"tbl":[],"clb":[],"gbl":[],"lns":null,"ifl":"image-150","tlx":0,"tly":0,"brx":1066,"bry":1605},{"ibl":[],"tbl":[],"clb":[],"gbl":[],"lns":null,"ifl":"image-151","tlx":0,"tly":0,"brx":1069,"bry":1607},{"ibl":[],"tbl":[],"clb":[],"gbl":[],"lns":null,"ifl":"image-152","tlx":0,"tly":0,"brx":1066,"bry":1606},{"ibl":[],"tbl":[],"clb":[],"gbl":[],"lns":null,"ifl":"image-153","tlx":0,"tly":0,"brx":1067,"bry":1606},{"ibl":[],"tbl":[],"clb":[],"gbl":[],"lns":null,"ifl":"image-154","tlx":0,"tly":0,"brx":1066,"bry":1605},{"ibl":[],"tbl":[],"clb":[],"gbl":[],"lns":null,"ifl":"image-155","tlx":0,"tly":0,"brx":1066,"bry":1605},{"ibl":[],"tbl":[],"clb":[],"gbl":[],"lns":null,"ifl":"image-156","tlx":0,"tly":0,"brx":1066,"bry":1605},{"ibl":[],"tbl":[],"clb":[],"gbl":[],"lns":null,"ifl":"image-157","tlx":0,"tly":0,"brx":1066,"bry":1605},{"ibl":[],"tbl":[],"clb":[],"gbl":[],"lns":null,"ifl":"image-158","tlx":0,"tly":0,"brx":1066,"bry":1606},{"ibl":[],"tbl":[],"clb":[],"gbl":[],"lns":null,"ifl":"image-159","tlx":0,"tly":0,"brx":1067,"bry":1606},{"ibl":[],"tbl":[],"clb":[],"gbl":[],"lns":null,"ifl":"image-160","tlx":0,"tly":0,"brx":1066,"bry":1605},{"ibl":[],"tbl":[],"clb":[],"gbl":[],"lns":null,"ifl":"image-161","tlx":0,"tly":0,"brx":1066,"bry":1606},{"ibl":[],"tbl":[],"clb":[],"gbl":[],"lns":null,"ifl":"image-162","tlx":0,"tly":0,"brx":1066,"bry":1605},{"ibl":[],"tbl":[],"clb":[],"gbl":[],"lns":null,"ifl":"image-163","tlx":0,"tly":0,"brx":1066,"bry":1605},{"ibl":[],"tbl":[],"clb":[],"gbl":[],"lns":null,"ifl":"image-164","tlx":0,"tly":0,"brx":1066,"bry":1605},{"ibl":[],"tbl":[],"clb":[],"gbl":[],"lns":null,"ifl":"image-165","tlx":0,"tly":0,"brx":1066,"bry":1606},{"ibl":[],"tbl":[],"clb":[],"gbl":[],"lns":null,"ifl":"image-166","tlx":0,"tly":0,"brx":1066,"bry":1606},{"ibl":[],"tbl":[],"clb":[],"gbl":[],"lns":null,"ifl":"image-167","tlx":0,"tly":0,"brx":1067,"bry":1606},{"ibl":[],"tbl":[],"clb":[],"gbl":[],"lns":null,"ifl":"image-168","tlx":0,"tly":0,"brx":1067,"bry":1606},{"ibl":[],"tbl":[],"clb":[],"gbl":[],"lns":null,"ifl":"image-169","tlx":0,"tly":0,"brx":1068,"bry":1607},{"ibl":[],"tbl":[],"clb":[],"gbl":[],"lns":null,"ifl":"image-170","tlx":0,"tly":0,"brx":1066,"bry":1605},{"ibl":[],"tbl":[],"clb":[],"gbl":[],"lns":null,"ifl":"image-171","tlx":0,"tly":0,"brx":1066,"bry":1606},{"ibl":[],"tbl":[],"clb":[],"gbl":[],"lns":null,"ifl":"image-172","tlx":0,"tly":0,"brx":1066,"bry":1605},{"ibl":[],"tbl":[],"clb":[],"gbl":[],"lns":null,"ifl":"image-173","tlx":0,"tly":0,"brx":1068,"bry":1607},{"ibl":[],"tbl":[],"clb":[],"gbl":[],"lns":null,"ifl":"image-174","tlx":0,"tly":0,"brx":1066,"bry":1606},{"ibl":[],"tbl":[],"clb":[],"gbl":[],"lns":null,"ifl":"image-175","tlx":0,"tly":0,"brx":1066,"bry":1606},{"ibl":[],"tbl":[],"clb":[],"gbl":[],"lns":null,"ifl":"image-176","tlx":0,"tly":0,"brx":1066,"bry":1605},{"ibl":[],"tbl":[],"clb":[],"gbl":[],"lns":null,"ifl":"image-177","tlx":0,"tly":0,"brx":1066,"bry":1606},{"ibl":[],"tbl":[],"clb":[],"gbl":[],"lns":null,"ifl":"image-178","tlx":0,"tly":0,"brx":1066,"bry":1605},{"ibl":[],"tbl":[],"clb":[],"gbl":[],"lns":null,"ifl":"image-179","tlx":0,"tly":0,"brx":1066,"bry":1605},{"ibl":[],"tbl":[],"clb":[],"gbl":[],"lns":null,"ifl":"image-180","tlx":0,"tly":0,"brx":1066,"bry":1606},{"ibl":[],"tbl":[],"clb":[],"gbl":[],"lns":null,"ifl":"image-181","tlx":0,"tly":0,"brx":1067,"bry":1606},{"ibl":[],"tbl":[],"clb":[],"gbl":[],"lns":null,"ifl":"image-182","tlx":0,"tly":0,"brx":1066,"bry":1606},{"ibl":[],"tbl":[],"clb":[],"gbl":[],"lns":null,"ifl":"image-183","tlx":0,"tly":0,"brx":1066,"bry":1605},{"ibl":[],"tbl":[],"clb":[],"gbl":[],"lns":null,"ifl":"image-184","tlx":0,"tly":0,"brx":1068,"bry":1607},{"ibl":[],"tbl":[],"clb":[],"gbl":[],"lns":null,"ifl":"image-185","tlx":0,"tly":0,"brx":1066,"bry":1605},{"ibl":[{"tlx":194,"tly":404,"brx":874,"bry":764}],"tbl":[],"clb":[],"gbl":[],"lns":null,"ifl":"image-186","tlx":0,"tly":0,"brx":1069,"bry":1608},{"ibl":[],"tbl":[],"clb":[],"gbl":[],"lns":null,"ifl":"image-187","tlx":0,"tly":0,"brx":1066,"bry":1606},{"ibl":[],"tbl":[],"clb":[],"gbl":[],"lns":null,"ifl":"image-188","tlx":0,"tly":0,"brx":1066,"bry":1606},{"ibl":[],"tbl":[],"clb":[],"gbl":[],"lns":null,"ifl":"image-189","tlx":0,"tly":0,"brx":1073,"bry":1610},{"ibl":[],"tbl":[],"clb":[],"gbl":[],"lns":null,"ifl":"image-190","tlx":0,"tly":0,"brx":1066,"bry":1605},{"ibl":[],"tbl":[],"clb":[],"gbl":[],"lns":null,"ifl":"image-191","tlx":0,"tly":0,"brx":1066,"bry":1606},{"ibl":[],"tbl":[],"clb":[],"gbl":[],"lns":null,"ifl":"image-192","tlx":0,"tly":0,"brx":1066,"bry":1605},{"ibl":[],"tbl":[],"clb":[],"gbl":[],"lns":null,"ifl":"image-193","tlx":0,"tly":0,"brx":1066,"bry":1605},{"ibl":[],"tbl":[],"clb":[],"gbl":[],"lns":null,"ifl":"image-194","tlx":0,"tly":0,"brx":1066,"bry":1606},{"ibl":[],"tbl":[],"clb":[],"gbl":[],"lns":null,"ifl":"image-195","tlx":0,"tly":0,"brx":1067,"bry":1606},{"ibl":[],"tbl":[],"clb":[],"gbl":[],"lns":null,"ifl":"image-196","tlx":0,"tly":0,"brx":1066,"bry":1606},{"ibl":[],"tbl":[],"clb":[],"gbl":[],"lns":null,"ifl":"image-197","tlx":0,"tly":0,"brx":1066,"bry":1605},{"ibl":[],"tbl":[],"clb":[],"gbl":[],"lns":null,"ifl":"image-198","tlx":0,"tly":0,"brx":1066,"bry":1605},{"ibl":[],"tbl":[],"clb":[],"gbl":[],"lns":null,"ifl":"image-199","tlx":0,"tly":0,"brx":1066,"bry":1606},{"ibl":[],"tbl":[],"clb":[],"gbl":[],"lns":null,"ifl":"image-200","tlx":0,"tly":0,"brx":1066,"bry":1606},{"ibl":[],"tbl":[],"clb":[],"gbl":[],"lns":null,"ifl":"image-201","tlx":0,"tly":0,"brx":1068,"bry":1607},{"ibl":[],"tbl":[],"clb":[],"gbl":[],"lns":null,"ifl":"image-202","tlx":0,"tly":0,"brx":1066,"bry":1605},{"ibl":[],"tbl":[],"clb":[],"gbl":[],"lns":null,"ifl":"image-203","tlx":0,"tly":0,"brx":1067,"bry":1606},{"ibl":[],"tbl":[],"clb":[],"gbl":[],"lns":null,"ifl":"image-204","tlx":0,"tly":0,"brx":1066,"bry":1606},{"ibl":[],"tbl":[],"clb":[],"gbl":[],"lns":null,"ifl":"image-205","tlx":0,"tly":0,"brx":1066,"bry":1606},{"ibl":[],"tbl":[],"clb":[],"gbl":[],"lns":null,"ifl":"image-206","tlx":0,"tly":0,"brx":1066,"bry":1605},{"ibl":[],"tbl":[],"clb":[],"gbl":[],"lns":null,"ifl":"image-207","tlx":0,"tly":0,"brx":1066,"bry":1606},{"ibl":[],"tbl":[],"clb":[],"gbl":[],"lns":null,"ifl":"image-208","tlx":0,"tly":0,"brx":1067,"bry":1606},{"ibl":[],"tbl":[],"clb":[],"gbl":[],"lns":null,"ifl":"image-209","tlx":0,"tly":0,"brx":1066,"bry":1606},{"ibl":[],"tbl":[],"clb":[],"gbl":[],"lns":null,"ifl":"image-210","tlx":0,"tly":0,"brx":1066,"bry":1606},{"ibl":[],"tbl":[],"clb":[],"gbl":[],"lns":null,"ifl":"image-211","tlx":0,"tly":0,"brx":1066,"bry":1606},{"ibl":[],"tbl":[],"clb":[],"gbl":[],"lns":null,"ifl":"image-212","tlx":0,"tly":0,"brx":1066,"bry":1605},{"ibl":[],"tbl":[],"clb":[],"gbl":[],"lns":null,"ifl":"image-213","tlx":0,"tly":0,"brx":1066,"bry":1606},{"ibl":[],"tbl":[],"clb":[],"gbl":[],"lns":null,"ifl":"image-214","tlx":0,"tly":0,"brx":1066,"bry":1605},{"ibl":[],"tbl":[],"clb":[],"gbl":[],"lns":null,"ifl":"image-215","tlx":0,"tly":0,"brx":1066,"bry":1606},{"ibl":[],"tbl":[],"clb":[],"gbl":[],"lns":null,"ifl":"image-216","tlx":0,"tly":0,"brx":1066,"bry":1606},{"ibl":[],"tbl":[],"clb":[],"gbl":[],"lns":null,"ifl":"image-217","tlx":0,"tly":0,"brx":1066,"bry":1605},{"ibl":[],"tbl":[],"clb":[],"gbl":[],"lns":null,"ifl":"image-218","tlx":0,"tly":0,"brx":1066,"bry":1605},{"ibl":[],"tbl":[],"clb":[],"gbl":[],"lns":null,"ifl":"image-219","tlx":0,"tly":0,"brx":1068,"bry":1607},{"ibl":[],"tbl":[],"clb":[],"gbl":[],"lns":null,"ifl":"image-220","tlx":0,"tly":0,"brx":1066,"bry":1606},{"ibl":[],"tbl":[],"clb":[],"gbl":[],"lns":null,"ifl":"image-221","tlx":0,"tly":0,"brx":1066,"bry":1605},{"ibl":[],"tbl":[],"clb":[],"gbl":[],"lns":null,"ifl":"image-222","tlx":0,"tly":0,"brx":1066,"bry":1605},{"ibl":[],"tbl":[],"clb":[],"gbl":[],"lns":null,"ifl":"image-223","tlx":0,"tly":0,"brx":1066,"bry":1606},{"ibl":[],"tbl":[],"clb":[],"gbl":[],"lns":null,"ifl":"image-224","tlx":0,"tly":0,"brx":1066,"bry":1606},{"ibl":[],"tbl":[],"clb":[],"gbl":[],"lns":null,"ifl":"image-225","tlx":0,"tly":0,"brx":1066,"bry":1605},{"ibl":[],"tbl":[],"clb":[],"gbl":[],"lns":null,"ifl":"image-226","tlx":0,"tly":0,"brx":1066,"bry":1606},{"ibl":[],"tbl":[],"clb":[],"gbl":[],"lns":null,"ifl":"image-227","tlx":0,"tly":0,"brx":1066,"bry":1606},{"ibl":[],"tbl":[],"clb":[],"gbl":[],"lns":null,"ifl":"image-228","tlx":0,"tly":0,"brx":1067,"bry":1606},{"ibl":[],"tbl":[],"clb":[],"gbl":[],"lns":null,"ifl":"image-229","tlx":0,"tly":0,"brx":1066,"bry":1605},{"ibl":[],"tbl":[],"clb":[],"gbl":[],"lns":null,"ifl":"image-230","tlx":0,"tly":0,"brx":1066,"bry":1606},{"ibl":[],"tbl":[],"clb":[],"gbl":[],"lns":null,"ifl":"image-231","tlx":0,"tly":0,"brx":1066,"bry":1606},{"ibl":[],"tbl":[],"clb":[],"gbl":[],"lns":null,"ifl":"image-232","tlx":0,"tly":0,"brx":1066,"bry":1605},{"ibl":[],"tbl":[],"clb":[],"gbl":[],"lns":null,"ifl":"image-233","tlx":0,"tly":0,"brx":1066,"bry":1605},{"ibl":[],"tbl":[],"clb":[],"gbl":[],"lns":null,"ifl":"image-234","tlx":0,"tly":0,"brx":1066,"bry":1605},{"ibl":[],"tbl":[],"clb":[],"gbl":[],"lns":null,"ifl":"image-235","tlx":0,"tly":0,"brx":1066,"bry":1606},{"ibl":[],"tbl":[],"clb":[],"gbl":[],"lns":null,"ifl":"image-236","tlx":0,"tly":0,"brx":1066,"bry":1606},{"ibl":[],"tbl":[],"clb":[],"gbl":[],"lns":null,"ifl":"image-237","tlx":0,"tly":0,"brx":1066,"bry":1605},{"ibl":[],"tbl":[],"clb":[],"gbl":[],"lns":null,"ifl":"image-238","tlx":0,"tly":0,"brx":1066,"bry":1605},{"ibl":[],"tbl":[],"clb":[],"gbl":[],"lns":null,"ifl":"image-239","tlx":0,"tly":0,"brx":1067,"bry":1606},{"ibl":[],"tbl":[],"clb":[],"gbl":[],"lns":null,"ifl":"image-240","tlx":0,"tly":0,"brx":1066,"bry":1605},{"ibl":[],"tbl":[],"clb":[],"gbl":[],"lns":null,"ifl":"image-241","tlx":0,"tly":0,"brx":1066,"bry":1606},{"ibl":[],"tbl":[],"clb":[],"gbl":[],"lns":null,"ifl":"image-242","tlx":0,"tly":0,"brx":1066,"bry":1605},{"ibl":[],"tbl":[],"clb":[],"gbl":[],"lns":null,"ifl":"image-243","tlx":0,"tly":0,"brx":1066,"bry":1605},{"ibl":[],"tbl":[],"clb":[],"gbl":[],"lns":null,"ifl":"image-244","tlx":0,"tly":0,"brx":1066,"bry":1606},{"ibl":[],"tbl":[],"clb":[],"gbl":[],"lns":null,"ifl":"image-245","tlx":0,"tly":0,"brx":1066,"bry":1606},{"ibl":[],"tbl":[],"clb":[],"gbl":[],"lns":null,"ifl":"image-246","tlx":0,"tly":0,"brx":1066,"bry":1605},{"ibl":[],"tbl":[],"clb":[],"gbl":[],"lns":null,"ifl":"image-247","tlx":0,"tly":0,"brx":1066,"bry":1606},{"ibl":[],"tbl":[],"clb":[],"gbl":[],"lns":null,"ifl":"image-248","tlx":0,"tly":0,"brx":1066,"bry":1606},{"ibl":[],"tbl":[],"clb":[],"gbl":[],"lns":null,"ifl":"image-249","tlx":0,"tly":0,"brx":1066,"bry":1606},{"ibl":[],"tbl":[],"clb":[],"gbl":[],"lns":null,"ifl":"image-250","tlx":0,"tly":0,"brx":1066,"bry":1606},{"ibl":[],"tbl":[],"clb":[],"gbl":[],"lns":null,"ifl":"image-251","tlx":0,"tly":0,"brx":1066,"bry":1605},{"ibl":[],"tbl":[],"clb":[],"gbl":[],"lns":null,"ifl":"image-252","tlx":0,"tly":0,"brx":1066,"bry":1605},{"ibl":[],"tbl":[],"clb":[],"gbl":[],"lns":null,"ifl":"image-253","tlx":0,"tly":0,"brx":1066,"bry":1606},{"ibl":[],"tbl":[],"clb":[],"gbl":[],"lns":null,"ifl":"image-254","tlx":0,"tly":0,"brx":1066,"bry":1606},{"ibl":[],"tbl":[],"clb":[],"gbl":[],"lns":null,"ifl":"image-255","tlx":0,"tly":0,"brx":1066,"bry":1606},{"ibl":[{"tlx":76,"tly":445,"brx":996,"bry":965}],"tbl":[],"clb":[],"gbl":[],"lns":null,"ifl":"image-256","tlx":0,"tly":0,"brx":1072,"bry":1610},{"ibl":[],"tbl":[],"clb":[],"gbl":[],"lns":null,"ifl":"image-257","tlx":0,"tly":0,"brx":1066,"bry":1605},{"ibl":[],"tbl":[],"clb":[],"gbl":[],"lns":null,"ifl":"image-258","tlx":0,"tly":0,"brx":1066,"bry":1605},{"ibl":[],"tbl":[],"clb":[],"gbl":[],"lns":null,"ifl":"image-259","tlx":0,"tly":0,"brx":1066,"bry":1606},{"ibl":[],"tbl":[],"clb":[],"gbl":[],"lns":null,"ifl":"image-260","tlx":0,"tly":0,"brx":1066,"bry":1605},{"ibl":[],"tbl":[],"clb":[],"gbl":[],"lns":null,"ifl":"image-261","tlx":0,"tly":0,"brx":1066,"bry":1605},{"ibl":[],"tbl":[],"clb":[],"gbl":[],"lns":null,"ifl":"image-262","tlx":0,"tly":0,"brx":1066,"bry":1605},{"ibl":[],"tbl":[],"clb":[],"gbl":[],"lns":null,"ifl":"image-263","tlx":0,"tly":0,"brx":1066,"bry":1606},{"ibl":[],"tbl":[],"clb":[],"gbl":[],"lns":null,"ifl":"image-264","tlx":0,"tly":0,"brx":1066,"bry":1605},{"ibl":[],"tbl":[],"clb":[],"gbl":[],"lns":null,"ifl":"image-265","tlx":0,"tly":0,"brx":1066,"bry":1605},{"ibl":[],"tbl":[],"clb":[],"gbl":[],"lns":null,"ifl":"image-266","tlx":0,"tly":0,"brx":1066,"bry":1605},{"ibl":[],"tbl":[],"clb":[],"gbl":[],"lns":null,"ifl":"image-267","tlx":0,"tly":0,"brx":1066,"bry":1605},{"ibl":[],"tbl":[],"clb":[],"gbl":[],"lns":null,"ifl":"image-268","tlx":0,"tly":0,"brx":1066,"bry":1606},{"ibl":[],"tbl":[],"clb":[],"gbl":[],"lns":null,"ifl":"image-269","tlx":0,"tly":0,"brx":1066,"bry":1606},{"ibl":[],"tbl":[],"clb":[],"gbl":[],"lns":null,"ifl":"image-270","tlx":0,"tly":0,"brx":1066,"bry":1606},{"ibl":[],"tbl":[],"clb":[],"gbl":[],"lns":null,"ifl":"image-271","tlx":0,"tly":0,"brx":1066,"bry":1605},{"ibl":[],"tbl":[],"clb":[],"gbl":[],"lns":null,"ifl":"image-272","tlx":0,"tly":0,"brx":1067,"bry":1606},{"ibl":[],"tbl":[],"clb":[],"gbl":[],"lns":null,"ifl":"image-273","tlx":0,"tly":0,"brx":1066,"bry":1606},{"ibl":[],"tbl":[],"clb":[],"gbl":[],"lns":null,"ifl":"image-274","tlx":0,"tly":0,"brx":1066,"bry":1605},{"ibl":[],"tbl":[],"clb":[],"gbl":[],"lns":null,"ifl":"image-275","tlx":0,"tly":0,"brx":1066,"bry":1606},{"ibl":[],"tbl":[],"clb":[],"gbl":[],"lns":null,"ifl":"image-276","tlx":0,"tly":0,"brx":1066,"bry":1605},{"ibl":[],"tbl":[],"clb":[],"gbl":[],"lns":null,"ifl":"image-277","tlx":0,"tly":0,"brx":1069,"bry":1607},{"ibl":[],"tbl":[],"clb":[],"gbl":[],"lns":null,"ifl":"image-278","tlx":0,"tly":0,"brx":1068,"bry":1607},{"ibl":[],"tbl":[],"clb":[],"gbl":[],"lns":null,"ifl":"image-279","tlx":0,"tly":0,"brx":1066,"bry":1606},{"ibl":[],"tbl":[],"clb":[],"gbl":[],"lns":null,"ifl":"image-280","tlx":0,"tly":0,"brx":1066,"bry":1606},{"ibl":[],"tbl":[],"clb":[],"gbl":[],"lns":null,"ifl":"image-281","tlx":0,"tly":0,"brx":1066,"bry":1605},{"ibl":[],"tbl":[],"clb":[],"gbl":[],"lns":null,"ifl":"image-282","tlx":0,"tly":0,"brx":1067,"bry":1606},{"ibl":[],"tbl":[],"clb":[],"gbl":[],"lns":null,"ifl":"image-283","tlx":0,"tly":0,"brx":1068,"bry":1607},{"ibl":[],"tbl":[],"clb":[],"gbl":[],"lns":null,"ifl":"image-284","tlx":0,"tly":0,"brx":1066,"bry":1605},{"ibl":[],"tbl":[],"clb":[],"gbl":[],"lns":null,"ifl":"image-285","tlx":0,"tly":0,"brx":1066,"bry":1605},{"ibl":[],"tbl":[],"clb":[],"gbl":[],"lns":null,"ifl":"image-286","tlx":0,"tly":0,"brx":1066,"bry":1605},{"ibl":[],"tbl":[],"clb":[],"gbl":[],"lns":null,"ifl":"image-287","tlx":0,"tly":0,"brx":1066,"bry":1605},{"ibl":[],"tbl":[],"clb":[],"gbl":[],"lns":null,"ifl":"image-288","tlx":0,"tly":0,"brx":1066,"bry":1605},{"ibl":[],"tbl":[],"clb":[],"gbl":[],"lns":null,"ifl":"image-289","tlx":0,"tly":0,"brx":1066,"bry":1606},{"ibl":[],"tbl":[],"clb":[],"gbl":[],"lns":null,"ifl":"image-290","tlx":0,"tly":0,"brx":1066,"bry":1605},{"ibl":[],"tbl":[],"clb":[],"gbl":[],"lns":null,"ifl":"image-291","tlx":0,"tly":0,"brx":1066,"bry":1606},{"ibl":[],"tbl":[],"clb":[],"gbl":[],"lns":null,"ifl":"image-292","tlx":0,"tly":0,"brx":1066,"bry":1606},{"ibl":[],"tbl":[],"clb":[],"gbl":[],"lns":null,"ifl":"image-293","tlx":0,"tly":0,"brx":1066,"bry":1606},{"ibl":[],"tbl":[],"clb":[],"gbl":[],"lns":null,"ifl":"image-294","tlx":0,"tly":0,"brx":1066,"bry":1605},{"ibl":[{"tlx":255,"tly":284,"brx":815,"bry":364}],"tbl":[],"clb":[],"gbl":[],"lns":null,"ifl":"image-295","tlx":0,"tly":0,"brx":1070,"bry":1608},{"ibl":[],"tbl":[],"clb":[],"gbl":[],"lns":null,"ifl":"image-296","tlx":0,"tly":0,"brx":1066,"bry":1605},{"ibl":[],"tbl":[],"clb":[],"gbl":[],"lns":null,"ifl":"image-297","tlx":0,"tly":0,"brx":1066,"bry":1606},{"ibl":[],"tbl":[],"clb":[],"gbl":[],"lns":null,"ifl":"image-298","tlx":0,"tly":0,"brx":1066,"bry":1605},{"ibl":[],"tbl":[],"clb":[],"gbl":[],"lns":null,"ifl":"image-299","tlx":0,"tly":0,"brx":1066,"bry":1606},{"ibl":[],"tbl":[],"clb":[],"gbl":[],"lns":null,"ifl":"image-300","tlx":0,"tly":0,"brx":1066,"bry":1605},{"ibl":[],"tbl":[],"clb":[],"gbl":[],"lns":null,"ifl":"image-301","tlx":0,"tly":0,"brx":1066,"bry":1605},{"ibl":[],"tbl":[],"clb":[],"gbl":[],"lns":null,"ifl":"image-302","tlx":0,"tly":0,"brx":1066,"bry":1605},{"ibl":[],"tbl":[],"clb":[],"gbl":[],"lns":null,"ifl":"image-303","tlx":0,"tly":0,"brx":1066,"bry":1605},{"ibl":[{"tlx":333,"tly":322,"brx":773,"bry":442}],"tbl":[],"clb":[],"gbl":[],"lns":null,"ifl":"image-304","tlx":0,"tly":0,"brx":1066,"bry":1605},{"ibl":[],"tbl":[],"clb":[],"gbl":[],"lns":null,"ifl":"image-305","tlx":0,"tly":0,"brx":1066,"bry":1606},{"ibl":[],"tbl":[],"clb":[],"gbl":[],"lns":null,"ifl":"image-306","tlx":0,"tly":0,"brx":1066,"bry":1606},{"ibl":[],"tbl":[],"clb":[],"gbl":[],"lns":null,"ifl":"image-307","tlx":0,"tly":0,"brx":1066,"bry":1606},{"ibl":[],"tbl":[],"clb":[],"gbl":[],"lns":null,"ifl":"image-308","tlx":0,"tly":0,"brx":1067,"bry":1606},{"ibl":[{"tlx":373,"tly":1442,"brx":773,"bry":1522}],"tbl":[],"clb":[],"gbl":[],"lns":null,"ifl":"image-309","tlx":0,"tly":0,"brx":1066,"bry":1605},{"ibl":[],"tbl":[],"clb":[],"gbl":[],"lns":null,"ifl":"image-310","tlx":0,"tly":0,"brx":1066,"bry":1605},{"ibl":[],"tbl":[],"clb":[],"gbl":[],"lns":null,"ifl":"image-311","tlx":0,"tly":0,"brx":1066,"bry":1605},{"ibl":[],"tbl":[],"clb":[],"gbl":[],"lns":null,"ifl":"image-312","tlx":0,"tly":0,"brx":1066,"bry":1605},{"ibl":[],"tbl":[],"clb":[],"gbl":[],"lns":null,"ifl":"image-313","tlx":0,"tly":0,"brx":1066,"bry":1605},{"ibl":[],"tbl":[],"clb":[],"gbl":[],"lns":null,"ifl":"image-314","tlx":0,"tly":0,"brx":1067,"bry":1606},{"ibl":[],"tbl":[],"clb":[],"gbl":[],"lns":null,"ifl":"image-315","tlx":0,"tly":0,"brx":1067,"bry":1606},{"ibl":[],"tbl":[],"clb":[],"gbl":[],"lns":null,"ifl":"image-316","tlx":0,"tly":0,"brx":1066,"bry":1606},{"ibl":[],"tbl":[],"clb":[],"gbl":[],"lns":null,"ifl":"image-317","tlx":0,"tly":0,"brx":1066,"bry":1605},{"ibl":[],"tbl":[],"clb":[],"gbl":[],"lns":null,"ifl":"image-318","tlx":0,"tly":0,"brx":1067,"bry":1606},{"ibl":[],"tbl":[],"clb":[],"gbl":[],"lns":null,"ifl":"image-319","tlx":0,"tly":0,"brx":1070,"bry":1608},{"ibl":[],"tbl":[],"clb":[],"gbl":[],"lns":null,"ifl":"image-320","tlx":0,"tly":0,"brx":1066,"bry":1606},{"ibl":[],"tbl":[],"clb":[],"gbl":[],"lns":null,"ifl":"image-321","tlx":0,"tly":0,"brx":1066,"bry":1605},{"ibl":[],"tbl":[],"clb":[],"gbl":[],"lns":null,"ifl":"image-322","tlx":0,"tly":0,"brx":1066,"bry":1606},{"ibl":[],"tbl":[],"clb":[],"gbl":[],"lns":null,"ifl":"image-323","tlx":0,"tly":0,"brx":1066,"bry":1605},{"ibl":[],"tbl":[],"clb":[],"gbl":[],"lns":null,"ifl":"image-324","tlx":0,"tly":0,"brx":1066,"bry":1606},{"ibl":[],"tbl":[],"clb":[],"gbl":[],"lns":null,"ifl":"image-325","tlx":0,"tly":0,"brx":1066,"bry":1606},{"ibl":[],"tbl":[],"clb":[],"gbl":[],"lns":null,"ifl":"image-326","tlx":0,"tly":0,"brx":1066,"bry":1605},{"ibl":[],"tbl":[],"clb":[],"gbl":[],"lns":null,"ifl":"image-327","tlx":0,"tly":0,"brx":1066,"bry":1606},{"ibl":[],"tbl":[],"clb":[],"gbl":[],"lns":null,"ifl":"image-328","tlx":0,"tly":0,"brx":1067,"bry":1606},{"ibl":[],"tbl":[],"clb":[],"gbl":[],"lns":null,"ifl":"image-329","tlx":0,"tly":0,"brx":1066,"bry":1605},{"ibl":[],"tbl":[],"clb":[],"gbl":[],"lns":null,"ifl":"image-330","tlx":0,"tly":0,"brx":1066,"bry":1605},{"ibl":[],"tbl":[],"clb":[],"gbl":[],"lns":null,"ifl":"image-331","tlx":0,"tly":0,"brx":1066,"bry":1605},{"ibl":[],"tbl":[],"clb":[],"gbl":[],"lns":null,"ifl":"image-332","tlx":0,"tly":0,"brx":1066,"bry":1606},{"ibl":[],"tbl":[],"clb":[],"gbl":[],"lns":null,"ifl":"image-333","tlx":0,"tly":0,"brx":1066,"bry":1605},{"ibl":[],"tbl":[],"clb":[],"gbl":[],"lns":null,"ifl":"image-334","tlx":0,"tly":0,"brx":1066,"bry":1606},{"ibl":[{"tlx":353,"tly":1443,"brx":873,"bry":1523}],"tbl":[],"clb":[],"gbl":[],"lns":null,"ifl":"image-335","tlx":0,"tly":0,"brx":1066,"bry":1606},{"ibl":[{"tlx":333,"tly":163,"brx":853,"bry":243}],"tbl":[],"clb":[],"gbl":[],"lns":null,"ifl":"image-336","tlx":0,"tly":0,"brx":1066,"bry":1606},{"ibl":[],"tbl":[],"clb":[],"gbl":[],"lns":null,"ifl":"image-337","tlx":0,"tly":0,"brx":1066,"bry":1605},{"ibl":[],"tbl":[],"clb":[],"gbl":[],"lns":null,"ifl":"image-338","tlx":0,"tly":0,"brx":1066,"bry":1605},{"ibl":[],"tbl":[],"clb":[],"gbl":[],"lns":null,"ifl":"image-339","tlx":0,"tly":0,"brx":1066,"bry":1605},{"ibl":[],"tbl":[],"clb":[],"gbl":[],"lns":null,"ifl":"image-340","tlx":0,"tly":0,"brx":1067,"bry":1606},{"ibl":[],"tbl":[],"clb":[],"gbl":[],"lns":null,"ifl":"image-341","tlx":0,"tly":0,"brx":1066,"bry":1605},{"ibl":[],"tbl":[],"clb":[],"gbl":[],"lns":null,"ifl":"image-342","tlx":0,"tly":0,"brx":1066,"bry":1605},{"ibl":[],"tbl":[],"clb":[],"gbl":[],"lns":null,"ifl":"image-343","tlx":0,"tly":0,"brx":1066,"bry":1606},{"ibl":[],"tbl":[],"clb":[],"gbl":[],"lns":null,"ifl":"image-344","tlx":0,"tly":0,"brx":1066,"bry":1606},{"ibl":[],"tbl":[],"clb":[],"gbl":[],"lns":null,"ifl":"image-345","tlx":0,"tly":0,"brx":1066,"bry":1606},{"ibl":[],"tbl":[],"clb":[],"gbl":[],"lns":null,"ifl":"image-346","tlx":0,"tly":0,"brx":1068,"bry":1607},{"ibl":[],"tbl":[],"clb":[],"gbl":[],"lns":null,"ifl":"image-347","tlx":0,"tly":0,"brx":1066,"bry":1606},{"ibl":[],"tbl":[],"clb":[],"gbl":[],"lns":null,"ifl":"image-348","tlx":0,"tly":0,"brx":1067,"bry":1606},{"ibl":[],"tbl":[],"clb":[],"gbl":[],"lns":null,"ifl":"image-349","tlx":0,"tly":0,"brx":1066,"bry":1606},{"ibl":[],"tbl":[],"clb":[],"gbl":[],"lns":null,"ifl":"image-350","tlx":0,"tly":0,"brx":1067,"bry":1606},{"ibl":[],"tbl":[],"clb":[],"gbl":[],"lns":null,"ifl":"image-351","tlx":0,"tly":0,"brx":1066,"bry":1606},{"ibl":[],"tbl":[],"clb":[],"gbl":[],"lns":null,"ifl":"image-352","tlx":0,"tly":0,"brx":1067,"bry":1606},{"ibl":[],"tbl":[],"clb":[],"gbl":[],"lns":null,"ifl":"image-353","tlx":0,"tly":0,"brx":1066,"bry":1605},{"ibl":[],"tbl":[],"clb":[],"gbl":[],"lns":null,"ifl":"image-354","tlx":0,"tly":0,"brx":1066,"bry":1605},{"ibl":[],"tbl":[],"clb":[],"gbl":[],"lns":null,"ifl":"image-355","tlx":0,"tly":0,"brx":1066,"bry":1606},{"ibl":[{"tlx":393,"tly":763,"brx":793,"bry":824},{"tlx":253,"tly":843,"brx":893,"bry":883}],"tbl":[],"clb":[],"gbl":[],"lns":null,"ifl":"image-356","tlx":0,"tly":0,"brx":1066,"bry":1606},{"ibl":[{"tlx":73,"tly":1102,"brx":953,"bry":1542}],"tbl":[],"clb":[],"gbl":[],"lns":null,"ifl":"image-357","tlx":0,"tly":0,"brx":1066,"bry":1605},{"ibl":[{"tlx":73,"tly":142,"brx":993,"bry":342}],"tbl":[],"clb":[],"gbl":[],"lns":null,"ifl":"image-358","tlx":0,"tly":0,"brx":1066,"bry":1605},{"ibl":[],"tbl":[],"clb":[],"gbl":[],"lns":null,"ifl":"image-359","tlx":0,"tly":0,"brx":1066,"bry":1605},{"ibl":[{"tlx":373,"tly":823,"brx":761,"bry":883}],"tbl":[],"clb":[],"gbl":[],"lns":null,"ifl":"image-360","tlx":0,"tly":0,"brx":1066,"bry":1606},{"ibl":[{"tlx":133,"tly":123,"brx":933,"bry":150}],"tbl":[],"clb":[],"gbl":[],"lns":null,"ifl":"image-361","tlx":0,"tly":0,"brx":1066,"bry":1606},{"ibl":[],"tbl":[],"clb":[],"gbl":[],"lns":null,"ifl":"image-362","tlx":0,"tly":0,"brx":1066,"bry":1606},{"ibl":[],"tbl":[],"clb":[],"gbl":[],"lns":null,"ifl":"image-363","tlx":0,"tly":0,"brx":1068,"bry":1607},{"ibl":[],"tbl":[],"clb":[],"gbl":[],"lns":null,"ifl":"image-364","tlx":0,"tly":0,"brx":1066,"bry":1606},{"ibl":[],"tbl":[],"clb":[],"gbl":[],"lns":null,"ifl":"image-365","tlx":0,"tly":0,"brx":1067,"bry":1606},{"ibl":[],"tbl":[],"clb":[],"gbl":[],"lns":null,"ifl":"image-366","tlx":0,"tly":0,"brx":1066,"bry":1605},{"ibl":[],"tbl":[],"clb":[],"gbl":[],"lns":null,"ifl":"image-367","tlx":0,"tly":0,"brx":1067,"bry":1606},{"ibl":[],"tbl":[],"clb":[],"gbl":[],"lns":null,"ifl":"image-368","tlx":0,"tly":0,"brx":1066,"bry":1605},{"ibl":[],"tbl":[],"clb":[],"gbl":[],"lns":null,"ifl":"image-369","tlx":0,"tly":0,"brx":1068,"bry":1607},{"ibl":[],"tbl":[],"clb":[],"gbl":[],"lns":null,"ifl":"image-370","tlx":0,"tly":0,"brx":1066,"bry":1605},{"ibl":[],"tbl":[],"clb":[],"gbl":[],"lns":null,"ifl":"image-371","tlx":0,"tly":0,"brx":1066,"bry":1606},{"ibl":[],"tbl":[],"clb":[],"gbl":[],"lns":null,"ifl":"image-372","tlx":0,"tly":0,"brx":1066,"bry":1606},{"ibl":[],"tbl":[],"clb":[],"gbl":[],"lns":null,"ifl":"image-373","tlx":0,"tly":0,"brx":1066,"bry":1606},{"ibl":[],"tbl":[],"clb":[],"gbl":[],"lns":null,"ifl":"image-374","tlx":0,"tly":0,"brx":1066,"bry":1606},{"ibl":[],"tbl":[],"clb":[],"gbl":[],"lns":null,"ifl":"image-375","tlx":0,"tly":0,"brx":1066,"bry":1605},{"ibl":[],"tbl":[],"clb":[],"gbl":[],"lns":null,"ifl":"image-376","tlx":0,"tly":0,"brx":1066,"bry":1605},{"ibl":[],"tbl":[],"clb":[],"gbl":[],"lns":null,"ifl":"image-377","tlx":0,"tly":0,"brx":1067,"bry":1606},{"ibl":[],"tbl":[],"clb":[],"gbl":[],"lns":null,"ifl":"image-378","tlx":0,"tly":0,"brx":1066,"bry":1606},{"ibl":[],"tbl":[],"clb":[],"gbl":[],"lns":null,"ifl":"image-379","tlx":0,"tly":0,"brx":1066,"bry":1605},{"ibl":[],"tbl":[],"clb":[],"gbl":[],"lns":null,"ifl":"image-380","tlx":0,"tly":0,"brx":1066,"bry":1606},{"ibl":[],"tbl":[],"clb":[],"gbl":[],"lns":null,"ifl":"image-381","tlx":0,"tly":0,"brx":1068,"bry":1607},{"ibl":[],"tbl":[],"clb":[],"gbl":[],"lns":null,"ifl":"image-382","tlx":0,"tly":0,"brx":1067,"bry":1606},{"ibl":[],"tbl":[],"clb":[],"gbl":[],"lns":null,"ifl":"image-383","tlx":0,"tly":0,"brx":1066,"bry":1605},{"ibl":[],"tbl":[],"clb":[],"gbl":[],"lns":null,"ifl":"image-384","tlx":0,"tly":0,"brx":1069,"bry":1607},{"ibl":[],"tbl":[],"clb":[],"gbl":[],"lns":null,"ifl":"image-385","tlx":0,"tly":0,"brx":1069,"bry":1607},{"ibl":[],"tbl":[],"clb":[],"gbl":[],"lns":null,"ifl":"image-386","tlx":0,"tly":0,"brx":1066,"bry":1605},{"ibl":[],"tbl":[],"clb":[],"gbl":[],"lns":null,"ifl":"image-387","tlx":0,"tly":0,"brx":1066,"bry":1606},{"ibl":[],"tbl":[],"clb":[],"gbl":[],"lns":null,"ifl":"image-388","tlx":0,"tly":0,"brx":1066,"bry":1605},{"ibl":[],"tbl":[],"clb":[],"gbl":[],"lns":null,"ifl":"image-389","tlx":0,"tly":0,"brx":1067,"bry":1606},{"ibl":[],"tbl":[],"clb":[],"gbl":[],"lns":null,"ifl":"image-390","tlx":0,"tly":0,"brx":1066,"bry":1605},{"ibl":[],"tbl":[],"clb":[],"gbl":[],"lns":null,"ifl":"image-391","tlx":0,"tly":0,"brx":1066,"bry":1605},{"ibl":[],"tbl":[],"clb":[],"gbl":[],"lns":null,"ifl":"image-392","tlx":0,"tly":0,"brx":1066,"bry":1605},{"ibl":[],"tbl":[],"clb":[],"gbl":[],"lns":null,"ifl":"image-393","tlx":0,"tly":0,"brx":1066,"bry":1605},{"ibl":[],"tbl":[],"clb":[],"gbl":[],"lns":null,"ifl":"image-394","tlx":0,"tly":0,"brx":1067,"bry":1606},{"ibl":[],"tbl":[],"clb":[],"gbl":[],"lns":null,"ifl":"image-395","tlx":0,"tly":0,"brx":1068,"bry":1607},{"ibl":[],"tbl":[],"clb":[],"gbl":[],"lns":null,"ifl":"image-396","tlx":0,"tly":0,"brx":1067,"bry":1606},{"ibl":[],"tbl":[],"clb":[],"gbl":[],"lns":null,"ifl":"image-397","tlx":0,"tly":0,"brx":1066,"bry":1606},{"ibl":[],"tbl":[],"clb":[],"gbl":[],"lns":null,"ifl":"image-398","tlx":0,"tly":0,"brx":1067,"bry":1606},{"ibl":[],"tbl":[],"clb":[],"gbl":[],"lns":null,"ifl":"image-399","tlx":0,"tly":0,"brx":1066,"bry":1606},{"ibl":[],"tbl":[],"clb":[],"gbl":[],"lns":null,"ifl":"image-400","tlx":0,"tly":0,"brx":1067,"bry":1607},{"ibl":[],"tbl":[],"clb":[],"gbl":[],"lns":null,"ifl":"image-401","tlx":0,"tly":0,"brx":1066,"bry":1605},{"ibl":[],"tbl":[],"clb":[],"gbl":[],"lns":null,"ifl":"image-402","tlx":0,"tly":0,"brx":1066,"bry":1606},{"ibl":[],"tbl":[],"clb":[],"gbl":[],"lns":null,"ifl":"image-403","tlx":0,"tly":0,"brx":1066,"bry":1606},{"ibl":[],"tbl":[],"clb":[],"gbl":[],"lns":null,"ifl":"image-404","tlx":0,"tly":0,"brx":1066,"bry":1606},{"ibl":[],"tbl":[],"clb":[],"gbl":[],"lns":null,"ifl":"image-405","tlx":0,"tly":0,"brx":1066,"bry":1605},{"ibl":[],"tbl":[],"clb":[],"gbl":[],"lns":null,"ifl":"image-406","tlx":0,"tly":0,"brx":1066,"bry":1605},{"ibl":[],"tbl":[],"clb":[],"gbl":[],"lns":null,"ifl":"image-407","tlx":0,"tly":0,"brx":1066,"bry":1606},{"ibl":[],"tbl":[],"clb":[],"gbl":[],"lns":null,"ifl":"image-408","tlx":0,"tly":0,"brx":1066,"bry":1606},{"ibl":[],"tbl":[],"clb":[],"gbl":[],"lns":null,"ifl":"image-409","tlx":0,"tly":0,"brx":1066,"bry":1605},{"ibl":[],"tbl":[],"clb":[],"gbl":[],"lns":null,"ifl":"image-410","tlx":0,"tly":0,"brx":1066,"bry":1606},{"ibl":[],"tbl":[],"clb":[],"gbl":[],"lns":null,"ifl":"image-411","tlx":0,"tly":0,"brx":1066,"bry":1605},{"ibl":[],"tbl":[],"clb":[],"gbl":[],"lns":null,"ifl":"image-412","tlx":0,"tly":0,"brx":1066,"bry":1605},{"ibl":[],"tbl":[],"clb":[],"gbl":[],"lns":null,"ifl":"image-413","tlx":0,"tly":0,"brx":1066,"bry":1606},{"ibl":[],"tbl":[],"clb":[],"gbl":[],"lns":null,"ifl":"image-414","tlx":0,"tly":0,"brx":1066,"bry":1605},{"ibl":[],"tbl":[],"clb":[],"gbl":[],"lns":null,"ifl":"image-415","tlx":0,"tly":0,"brx":1066,"bry":1606},{"ibl":[],"tbl":[],"clb":[],"gbl":[],"lns":null,"ifl":"image-416","tlx":0,"tly":0,"brx":1066,"bry":1606},{"ibl":[],"tbl":[],"clb":[],"gbl":[],"lns":null,"ifl":"image-417","tlx":0,"tly":0,"brx":1066,"bry":1606},{"ibl":[],"tbl":[],"clb":[],"gbl":[],"lns":null,"ifl":"image-418","tlx":0,"tly":0,"brx":1066,"bry":1606},{"ibl":[],"tbl":[],"clb":[],"gbl":[],"lns":null,"ifl":"image-419","tlx":0,"tly":0,"brx":1066,"bry":1606},{"ibl":[],"tbl":[],"clb":[],"gbl":[],"lns":null,"ifl":"image-420","tlx":0,"tly":0,"brx":1066,"bry":1606},{"ibl":[],"tbl":[],"clb":[],"gbl":[],"lns":null,"ifl":"image-421","tlx":0,"tly":0,"brx":1066,"bry":1606},{"ibl":[],"tbl":[],"clb":[],"gbl":[],"lns":null,"ifl":"image-422","tlx":0,"tly":0,"brx":1066,"bry":1606},{"ibl":[],"tbl":[],"clb":[],"gbl":[],"lns":null,"ifl":"image-423","tlx":0,"tly":0,"brx":1068,"bry":1607},{"ibl":[],"tbl":[],"clb":[],"gbl":[],"lns":null,"ifl":"image-424","tlx":0,"tly":0,"brx":1066,"bry":1605},{"ibl":[],"tbl":[],"clb":[],"gbl":[],"lns":null,"ifl":"image-425","tlx":0,"tly":0,"brx":1066,"bry":1605},{"ibl":[],"tbl":[],"clb":[],"gbl":[],"lns":null,"ifl":"image-426","tlx":0,"tly":0,"brx":1066,"bry":1606},{"ibl":[],"tbl":[],"clb":[],"gbl":[],"lns":null,"ifl":"image-427","tlx":0,"tly":0,"brx":1066,"bry":1605},{"ibl":[],"tbl":[],"clb":[],"gbl":[],"lns":null,"ifl":"image-428","tlx":0,"tly":0,"brx":1066,"bry":1606},{"ibl":[],"tbl":[],"clb":[],"gbl":[],"lns":null,"ifl":"image-429","tlx":0,"tly":0,"brx":1066,"bry":1606},{"ibl":[],"tbl":[],"clb":[],"gbl":[],"lns":null,"ifl":"image-430","tlx":0,"tly":0,"brx":1068,"bry":1607},{"ibl":[],"tbl":[],"clb":[],"gbl":[],"lns":null,"ifl":"image-431","tlx":0,"tly":0,"brx":1066,"bry":1605},{"ibl":[],"tbl":[],"clb":[],"gbl":[],"lns":null,"ifl":"image-432","tlx":0,"tly":0,"brx":1066,"bry":1606},{"ibl":[],"tbl":[],"clb":[],"gbl":[],"lns":null,"ifl":"image-433","tlx":0,"tly":0,"brx":1066,"bry":1605},{"ibl":[],"tbl":[],"clb":[],"gbl":[],"lns":null,"ifl":"image-434","tlx":0,"tly":0,"brx":1068,"bry":1607},{"ibl":[],"tbl":[],"clb":[],"gbl":[],"lns":null,"ifl":"image-435","tlx":0,"tly":0,"brx":1066,"bry":1606},{"ibl":[],"tbl":[],"clb":[],"gbl":[],"lns":null,"ifl":"image-436","tlx":0,"tly":0,"brx":1068,"bry":1607},{"ibl":[],"tbl":[],"clb":[],"gbl":[],"lns":null,"ifl":"image-437","tlx":0,"tly":0,"brx":1067,"bry":1606},{"ibl":[],"tbl":[],"clb":[],"gbl":[],"lns":null,"ifl":"image-438","tlx":0,"tly":0,"brx":1066,"bry":1606},{"ibl":[],"tbl":[],"clb":[],"gbl":[],"lns":null,"ifl":"image-439","tlx":0,"tly":0,"brx":1068,"bry":1607},{"ibl":[],"tbl":[],"clb":[],"gbl":[],"lns":null,"ifl":"image-440","tlx":0,"tly":0,"brx":1066,"bry":1606},{"ibl":[],"tbl":[],"clb":[],"gbl":[],"lns":null,"ifl":"image-441","tlx":0,"tly":0,"brx":1066,"bry":1606},{"ibl":[],"tbl":[],"clb":[],"gbl":[],"lns":null,"ifl":"image-442","tlx":0,"tly":0,"brx":1066,"bry":1605},{"ibl":[],"tbl":[],"clb":[],"gbl":[],"lns":null,"ifl":"image-443","tlx":0,"tly":0,"brx":1067,"bry":1606},{"ibl":[],"tbl":[],"clb":[],"gbl":[],"lns":null,"ifl":"image-444","tlx":0,"tly":0,"brx":1066,"bry":1605},{"ibl":[],"tbl":[],"clb":[],"gbl":[],"lns":null,"ifl":"image-445","tlx":0,"tly":0,"brx":1066,"bry":1605},{"ibl":[],"tbl":[],"clb":[],"gbl":[],"lns":null,"ifl":"image-446","tlx":0,"tly":0,"brx":1067,"bry":1606},{"ibl":[],"tbl":[],"clb":[],"gbl":[],"lns":null,"ifl":"image-447","tlx":0,"tly":0,"brx":1067,"bry":1606},{"ibl":[],"tbl":[],"clb":[],"gbl":[],"lns":null,"ifl":"image-448","tlx":0,"tly":0,"brx":1067,"bry":1606},{"ibl":[],"tbl":[],"clb":[],"gbl":[],"lns":null,"ifl":"image-449","tlx":0,"tly":0,"brx":1067,"bry":1606},{"ibl":[],"tbl":[],"clb":[],"gbl":[],"lns":null,"ifl":"image-450","tlx":0,"tly":0,"brx":1066,"bry":1606},{"ibl":[],"tbl":[],"clb":[],"gbl":[],"lns":null,"ifl":"image-451","tlx":0,"tly":0,"brx":1066,"bry":1606},{"ibl":[],"tbl":[],"clb":[],"gbl":[],"lns":null,"ifl":"image-452","tlx":0,"tly":0,"brx":1067,"bry":1606},{"ibl":[],"tbl":[],"clb":[],"gbl":[],"lns":null,"ifl":"image-453","tlx":0,"tly":0,"brx":1066,"bry":1606},{"ibl":[],"tbl":[],"clb":[],"gbl":[],"lns":null,"ifl":"image-454","tlx":0,"tly":0,"brx":1067,"bry":1606},{"ibl":[],"tbl":[],"clb":[],"gbl":[],"lns":null,"ifl":"image-455","tlx":0,"tly":0,"brx":1067,"bry":1606},{"ibl":[],"tbl":[],"clb":[],"gbl":[],"lns":null,"ifl":"image-456","tlx":0,"tly":0,"brx":1066,"bry":1605},{"ibl":[],"tbl":[],"clb":[],"gbl":[],"lns":null,"ifl":"image-457","tlx":0,"tly":0,"brx":1066,"bry":1605},{"ibl":[],"tbl":[],"clb":[],"gbl":[],"lns":null,"ifl":"image-458","tlx":0,"tly":0,"brx":1066,"bry":1606},{"ibl":[],"tbl":[],"clb":[],"gbl":[],"lns":null,"ifl":"image-459","tlx":0,"tly":0,"brx":1066,"bry":1605},{"ibl":[],"tbl":[],"clb":[],"gbl":[],"lns":null,"ifl":"image-460","tlx":0,"tly":0,"brx":1066,"bry":1605},{"ibl":[],"tbl":[],"clb":[],"gbl":[],"lns":null,"ifl":"image-461","tlx":0,"tly":0,"brx":1066,"bry":1605},{"ibl":[],"tbl":[],"clb":[],"gbl":[],"lns":null,"ifl":"image-462","tlx":0,"tly":0,"brx":1066,"bry":1606},{"ibl":[],"tbl":[],"clb":[],"gbl":[],"lns":null,"ifl":"image-463","tlx":0,"tly":0,"brx":1067,"bry":1606},{"ibl":[],"tbl":[],"clb":[],"gbl":[],"lns":null,"ifl":"image-464","tlx":0,"tly":0,"brx":1066,"bry":1606},{"ibl":[],"tbl":[],"clb":[],"gbl":[],"lns":null,"ifl":"image-465","tlx":0,"tly":0,"brx":1068,"bry":1607},{"ibl":[],"tbl":[],"clb":[],"gbl":[],"lns":null,"ifl":"image-466","tlx":0,"tly":0,"brx":1068,"bry":1607},{"ibl":[],"tbl":[],"clb":[],"gbl":[],"lns":null,"ifl":"image-467","tlx":0,"tly":0,"brx":1066,"bry":1605},{"ibl":[],"tbl":[],"clb":[],"gbl":[],"lns":null,"ifl":"image-468","tlx":0,"tly":0,"brx":1066,"bry":1606},{"ibl":[],"tbl":[],"clb":[],"gbl":[],"lns":null,"ifl":"image-469","tlx":0,"tly":0,"brx":1067,"bry":1606},{"ibl":[],"tbl":[],"clb":[],"gbl":[],"lns":null,"ifl":"image-470","tlx":0,"tly":0,"brx":1066,"bry":1606},{"ibl":[],"tbl":[],"clb":[],"gbl":[],"lns":null,"ifl":"image-471","tlx":0,"tly":0,"brx":1067,"bry":1606},{"ibl":[],"tbl":[],"clb":[],"gbl":[],"lns":null,"ifl":"image-472","tlx":0,"tly":0,"brx":1068,"bry":1607},{"ibl":[],"tbl":[],"clb":[],"gbl":[],"lns":null,"ifl":"image-473","tlx":0,"tly":0,"brx":1066,"bry":1606},{"ibl":[],"tbl":[],"clb":[],"gbl":[],"lns":null,"ifl":"image-474","tlx":0,"tly":0,"brx":1066,"bry":1606},{"ibl":[],"tbl":[],"clb":[],"gbl":[],"lns":null,"ifl":"image-475","tlx":0,"tly":0,"brx":1066,"bry":1606},{"ibl":[],"tbl":[],"clb":[],"gbl":[],"lns":null,"ifl":"image-476","tlx":0,"tly":0,"brx":1066,"bry":1606},{"ibl":[],"tbl":[],"clb":[],"gbl":[],"lns":null,"ifl":"image-477","tlx":0,"tly":0,"brx":1069,"bry":1607},{"ibl":[],"tbl":[],"clb":[],"gbl":[],"lns":null,"ifl":"image-478","tlx":0,"tly":0,"brx":1067,"bry":1606},{"ibl":[],"tbl":[],"clb":[],"gbl":[],"lns":null,"ifl":"image-479","tlx":0,"tly":0,"brx":1066,"bry":1606},{"ibl":[],"tbl":[],"clb":[],"gbl":[],"lns":null,"ifl":"image-480","tlx":0,"tly":0,"brx":1073,"bry":1610},{"ibl":[],"tbl":[],"clb":[],"gbl":[],"lns":null,"ifl":"image-481","tlx":0,"tly":0,"brx":1066,"bry":1606},{"ibl":[],"tbl":[],"clb":[],"gbl":[],"lns":null,"ifl":"image-482","tlx":0,"tly":0,"brx":1067,"bry":1606},{"ibl":[],"tbl":[],"clb":[],"gbl":[],"lns":null,"ifl":"image-483","tlx":0,"tly":0,"brx":1067,"bry":1606},{"ibl":[],"tbl":[],"clb":[],"gbl":[],"lns":null,"ifl":"image-484","tlx":0,"tly":0,"brx":1067,"bry":1606},{"ibl":[],"tbl":[],"clb":[],"gbl":[],"lns":null,"ifl":"image-485","tlx":0,"tly":0,"brx":1066,"bry":1606},{"ibl":[],"tbl":[],"clb":[],"gbl":[],"lns":null,"ifl":"image-486","tlx":0,"tly":0,"brx":1066,"bry":1605},{"ibl":[],"tbl":[],"clb":[],"gbl":[],"lns":null,"ifl":"image-487","tlx":0,"tly":0,"brx":1066,"bry":1605},{"ibl":[],"tbl":[],"clb":[],"gbl":[],"lns":null,"ifl":"image-488","tlx":0,"tly":0,"brx":1066,"bry":1605},{"ibl":[],"tbl":[],"clb":[],"gbl":[],"lns":null,"ifl":"image-489","tlx":0,"tly":0,"brx":1067,"bry":1606},{"ibl":[],"tbl":[],"clb":[],"gbl":[],"lns":null,"ifl":"image-490","tlx":0,"tly":0,"brx":1071,"bry":1609},{"ibl":[],"tbl":[],"clb":[],"gbl":[],"lns":null,"ifl":"image-491","tlx":0,"tly":0,"brx":1067,"bry":1606},{"ibl":[],"tbl":[],"clb":[],"gbl":[],"lns":null,"ifl":"image-492","tlx":0,"tly":0,"brx":1068,"bry":1607},{"ibl":[],"tbl":[],"clb":[],"gbl":[],"lns":null,"ifl":"image-493","tlx":0,"tly":0,"brx":1067,"bry":1606},{"ibl":[],"tbl":[],"clb":[],"gbl":[],"lns":null,"ifl":"image-494","tlx":0,"tly":0,"brx":1070,"bry":1608},{"ibl":[],"tbl":[],"clb":[],"gbl":[],"lns":null,"ifl":"image-495","tlx":0,"tly":0,"brx":1067,"bry":1606},{"ibl":[],"tbl":[],"clb":[],"gbl":[],"lns":null,"ifl":"image-496","tlx":0,"tly":0,"brx":1070,"bry":1608},{"ibl":[],"tbl":[],"clb":[],"gbl":[],"lns":null,"ifl":"image-497","tlx":0,"tly":0,"brx":1070,"bry":1608},{"ibl":[],"tbl":[],"clb":[],"gbl":[],"lns":null,"ifl":"image-498","tlx":0,"tly":0,"brx":1077,"bry":1613},{"ibl":[],"tbl":[],"clb":[],"gbl":[],"lns":null,"ifl":"image-499","tlx":0,"tly":0,"brx":1082,"bry":1616},{"ibl":[],"tbl":[],"clb":[],"gbl":[],"lns":null,"ifl":"image-500","tlx":0,"tly":0,"brx":1079,"bry":1614},{"ibl":[],"tbl":[],"clb":[],"gbl":[],"lns":null,"ifl":"image-501","tlx":0,"tly":0,"brx":1079,"bry":1614},{"ibl":[{"tlx":54,"tly":163,"brx":1014,"bry":1541}],"tbl":[],"clb":[],"gbl":[],"lns":null,"ifl":"image-502","tlx":0,"tly":0,"brx":1068,"bry":1607},{"ibl":[],"tbl":[],"clb":[],"gbl":[],"lns":null,"ifl":"image-503","tlx":0,"tly":0,"brx":1071,"bry":1609},{"ibl":[{"tlx":234,"tly":724,"brx":834,"bry":1564}],"tbl":[],"clb":[],"gbl":[],"lns":null,"ifl":"image-504","tlx":0,"tly":0,"brx":1069,"bry":1608}]}